sqlalchemy_dm/__init__.py
sqlalchemy_dm/base.py
sqlalchemy_dm/dmPython.py
sqlalchemy_dm/json.py
sqlalchemy_dm/types.py
sqlalchemy_dm-8.1.2.98.dist-info/LICENSE
sqlalchemy_dm-8.1.2.98.dist-info/METADATA
sqlalchemy_dm-8.1.2.98.dist-info/WHEEL
sqlalchemy_dm-8.1.2.98.dist-info/entry_points.txt
sqlalchemy_dm-8.1.2.98.dist-info/top_level.txt
sqlalchemy_dm-8.1.2.98.dist-info/RECORD
